sdk_passport/__init__.py
sdk_passport/admin.py
sdk_passport/apps.py
sdk_passport/models.py
sdk_passport/tests.py
sdk_passport/urls.py
sdk_passport/views.py
sdk_passport/migrations/__init__.py
sdk_passport_verify/__init__.py
sdk_passport_verify/asgi.py
sdk_passport_verify/settings.py
sdk_passport_verify/urls.py
sdk_passport_verify/wsgi.py
sdk_passport-0.1.dist-info/METADATA
sdk_passport-0.1.dist-info/WHEEL
sdk_passport-0.1.dist-info/top_level.txt
sdk_passport-0.1.dist-info/RECORD
