Metadata-Version: 2.1
Name: sdk-passport
Version: 0.1
Summary: A library for capturing image
Home-page: https://github.com/arijitdatta123/sdk_passport.git
Author: Arijit Datta
Author-email: dattarijit97@gmail.com
License: MIT
Keywords: password
Classifier: Development Status :: 5 - Production/Stable
Classifier: Intended Audience :: Education
Classifier: Operating System :: Microsoft :: Windows :: Windows 10
Classifier: License :: OSI Approved :: MIT License
Classifier: Programming Language :: Python :: 3
